{
    "animations": [
        {
            "offsets": [
                0,
                0
            ],
            "indices": [],
            "fps": 24,
            "anim": "idle",
            "loop": false,
            "name": "idle"
        },
        {
            "offsets": [
                0,
                0
            ],
            "indices": [],
            "fps": 24,
            "anim": "singLEFT",
            "loop": false,
            "name": "sing left"
        },
        {
            "offsets": [
                0,
                0
            ],
            "indices": [],
            "fps": 24,
            "anim": "singDOWN",
            "loop": false,
            "name": "sing down"
        },
        {
            "offsets": [
                0,
                0
            ],
            "indices": [],
            "fps": 24,
            "anim": "singUP",
            "loop": false,
            "name": "sing up"
        },
        {
            "offsets": [
                0,
                0
            ],
            "indices": [],
            "fps": 24,
            "anim": "singRIGHT",
            "loop": false,
            "name": "sing right"
        }
    ],
    "no_antialiasing": false,
    "image": "characters/zestyGlitch",
    "position": [
        40,
        0
    ],
    "healthicon": "zestyGlitch",
    "flip_x": false,
    "healthbar_colors": [
        255,
        255,
        255
    ],
    "camera_position": [
        -120,
        -20
    ],
    "sing_duration": 6.1,
    "scale": 1
}